{
  "97111": {
    "name": "Hiroki Ito",
    "teamName": "Japan",
    "teamAbbr": "JPN",
    "appearances": 1,
    "goals": 0,
    "assists": 0,
    "shots": 0,
    "shotsOnTarget": 0,
    "saves": 0,
    "yellowCards": 0,
    "redCards": 0,
    "minutesPlayed": 0
  },
  "119082": {
    "name": "Yuto Nagatomo",
    "teamName": "Japan",
    "teamAbbr": "JPN",
    "appearances": 1,
    "goals": 0,
    "assists": 0,
    "shots": 0,
    "shotsOnTarget": 0,
    "saves": 0,
    "yellowCards": 0,
    "redCards": 0,
    "minutesPlayed": 0
  },
  "159152": {
    "name": "Rani Khedira",
    "teamName": "Tunisia",
    "teamAbbr": "TUN",
    "appearances": 1,
    "goals": 0,
    "assists": 0,
    "shots": 0,
    "shotsOnTarget": 0,
    "saves": 0,
    "yellowCards": 0,
    "redCards": 0,
    "minutesPlayed": 0
  },
  "195253": {
    "name": "Sabri Ben Hessen",
    "teamName": "Tunisia",
    "teamAbbr": "TUN",
    "appearances": 1,
    "goals": 0,
    "assists": 0,
    "shots": 0,
    "shotsOnTarget": 0,
    "saves": 0,
    "yellowCards": 0,
    "redCards": 0,
    "minutesPlayed": 0
  },
  "202728": {
    "name": "Shogo Taniguchi",
    "teamName": "Japan",
    "teamAbbr": "JPN",
    "appearances": 1,
    "goals": 0,
    "assists": 0,
    "shots": 0,
    "shotsOnTarget": 0,
    "saves": 0,
    "yellowCards": 0,
    "redCards": 0,
    "minutesPlayed": 0
  },
  "209595": {
    "name": "Ellyes Skhiri",
    "teamName": "Tunisia",
    "teamAbbr": "TUN",
    "appearances": 1,
    "goals": 0,
    "assists": 0,
    "shots": 0,
    "shotsOnTarget": 0,
    "saves": 0,
    "yellowCards": 0,
    "redCards": 0,
    "minutesPlayed": 0
  },
  "219350": {
    "name": "Junya Ito",
    "teamName": "Japan",
    "teamAbbr": "JPN",
    "appearances": 1,
    "goals": 1,
    "assists": 0,
    "shots": 2,
    "shotsOnTarget": 1,
    "saves": 0,
    "yellowCards": 0,
    "redCards": 0,
    "minutesPlayed": 0
  },
  "219362": {
    "name": "Daichi Kamada",
    "teamName": "Japan",
    "teamAbbr": "JPN",
    "appearances": 1,
    "goals": 1,
    "assists": 0,
    "shots": 1,
    "shotsOnTarget": 1,
    "saves": 0,
    "yellowCards": 0,
    "redCards": 0,
    "minutesPlayed": 0
  },
  "219627": {
    "name": "Ritsu Doan",
    "teamName": "Japan",
    "teamAbbr": "JPN",
    "appearances": 1,
    "goals": 0,
    "assists": 0,
    "shots": 0,
    "shotsOnTarget": 0,
    "saves": 0,
    "yellowCards": 0,
    "redCards": 0,
    "minutesPlayed": 0,
    "headshot": "https://a.espncdn.com/i/headshots/soccer/players/full/219627.png"
  },
  "238004": {
    "name": "Takehiro Tomiyasu",
    "teamName": "Japan",
    "teamAbbr": "JPN",
    "appearances": 1,
    "goals": 0,
    "assists": 0,
    "shots": 1,
    "shotsOnTarget": 0,
    "saves": 0,
    "yellowCards": 0,
    "redCards": 0,
    "minutesPlayed": 0
  },
  "238016": {
    "name": "Koki Ogawa",
    "teamName": "Japan",
    "teamAbbr": "JPN",
    "appearances": 1,
    "goals": 0,
    "assists": 0,
    "shots": 0,
    "shotsOnTarget": 0,
    "saves": 0,
    "yellowCards": 0,
    "redCards": 0,
    "minutesPlayed": 0,
    "headshot": "https://a.espncdn.com/i/headshots/soccer/players/full/238016.png"
  },
  "238033": {
    "name": "Kou Itakura",
    "teamName": "Japan",
    "teamAbbr": "JPN",
    "appearances": 1,
    "goals": 0,
    "assists": 1,
    "shots": 0,
    "shotsOnTarget": 0,
    "saves": 0,
    "yellowCards": 0,
    "redCards": 0,
    "minutesPlayed": 0,
    "headshot": "https://a.espncdn.com/i/headshots/soccer/players/full/238033.png"
  },
  "240371": {
    "name": "Dylan Bronn",
    "teamName": "Tunisia",
    "teamAbbr": "TUN",
    "appearances": 1,
    "goals": 0,
    "assists": 0,
    "shots": 0,
    "shotsOnTarget": 0,
    "saves": 0,
    "yellowCards": 0,
    "redCards": 0,
    "minutesPlayed": 0
  },
  "240588": {
    "name": "Yan Valery",
    "teamName": "Tunisia",
    "teamAbbr": "TUN",
    "appearances": 1,
    "goals": 0,
    "assists": 0,
    "shots": 0,
    "shotsOnTarget": 0,
    "saves": 0,
    "yellowCards": 0,
    "redCards": 0,
    "minutesPlayed": 0
  },
  "253173": {
    "name": "Ao Tanaka",
    "teamName": "Japan",
    "teamAbbr": "JPN",
    "appearances": 1,
    "goals": 0,
    "assists": 0,
    "shots": 1,
    "shotsOnTarget": 0,
    "saves": 0,
    "yellowCards": 0,
    "redCards": 0,
    "minutesPlayed": 0
  },
  "255723": {
    "name": "Keisuke Osako",
    "teamName": "Japan",
    "teamAbbr": "JPN",
    "appearances": 1,
    "goals": 0,
    "assists": 0,
    "shots": 0,
    "shotsOnTarget": 0,
    "saves": 0,
    "yellowCards": 0,
    "redCards": 0,
    "minutesPlayed": 0
  },
  "258270": {
    "name": "Ayumu Seko",
    "teamName": "Japan",
    "teamAbbr": "JPN",
    "appearances": 1,
    "goals": 0,
    "assists": 0,
    "shots": 0,
    "shotsOnTarget": 0,
    "saves": 0,
    "yellowCards": 0,
    "redCards": 0,
    "minutesPlayed": 0
  },
  "265099": {
    "name": "Montassar Talbi",
    "teamName": "Tunisia",
    "teamAbbr": "TUN",
    "appearances": 1,
    "goals": 0,
    "assists": 0,
    "shots": 0,
    "shotsOnTarget": 0,
    "saves": 0,
    "yellowCards": 0,
    "redCards": 0,
    "minutesPlayed": 0
  },
  "265207": {
    "name": "Firas Chaouat",
    "teamName": "Tunisia",
    "teamAbbr": "TUN",
    "appearances": 1,
    "goals": 0,
    "assists": 0,
    "shots": 0,
    "shotsOnTarget": 0,
    "saves": 0,
    "yellowCards": 0,
    "redCards": 0,
    "minutesPlayed": 0
  },
  "265234": {
    "name": "Ali Abdi",
    "teamName": "Tunisia",
    "teamAbbr": "TUN",
    "appearances": 1,
    "goals": 0,
    "assists": 0,
    "shots": 0,
    "shotsOnTarget": 0,
    "saves": 0,
    "yellowCards": 0,
    "redCards": 0,
    "minutesPlayed": 0
  },
  "265272": {
    "name": "Aymen Dahmen",
    "teamName": "Tunisia",
    "teamAbbr": "TUN",
    "appearances": 1,
    "goals": 0,
    "assists": 0,
    "shots": 0,
    "shotsOnTarget": 0,
    "saves": 1,
    "yellowCards": 0,
    "redCards": 0,
    "minutesPlayed": 0
  },
  "265953": {
    "name": "Keito Nakamura",
    "teamName": "Japan",
    "teamAbbr": "JPN",
    "appearances": 1,
    "goals": 0,
    "assists": 1,
    "shots": 1,
    "shotsOnTarget": 0,
    "saves": 0,
    "yellowCards": 0,
    "redCards": 0,
    "minutesPlayed": 0
  },
  "265958": {
    "name": "Zion Suzuki",
    "teamName": "Japan",
    "teamAbbr": "JPN",
    "appearances": 1,
    "goals": 0,
    "assists": 0,
    "shots": 0,
    "shotsOnTarget": 0,
    "saves": 0,
    "yellowCards": 0,
    "redCards": 0,
    "minutesPlayed": 0
  },
  "265965": {
    "name": "Yukinari Sugawara",
    "teamName": "Japan",
    "teamAbbr": "JPN",
    "appearances": 1,
    "goals": 0,
    "assists": 0,
    "shots": 0,
    "shotsOnTarget": 0,
    "saves": 0,
    "yellowCards": 0,
    "redCards": 0,
    "minutesPlayed": 0,
    "headshot": "https://a.espncdn.com/i/headshots/soccer/players/full/265965.png"
  },
  "273170": {
    "name": "Mortadha Ben Ouanes",
    "teamName": "Tunisia",
    "teamAbbr": "TUN",
    "appearances": 1,
    "goals": 0,
    "assists": 0,
    "shots": 0,
    "shotsOnTarget": 0,
    "saves": 0,
    "yellowCards": 0,
    "redCards": 0,
    "minutesPlayed": 0
  },
  "274277": {
    "name": "Ayase Ueda",
    "teamName": "Japan",
    "teamAbbr": "JPN",
    "appearances": 1,
    "goals": 2,
    "assists": 1,
    "shots": 5,
    "shotsOnTarget": 3,
    "saves": 0,
    "yellowCards": 0,
    "redCards": 0,
    "minutesPlayed": 0
  },
  "276279": {
    "name": "Tsuyoshi Watanabe",
    "teamName": "Japan",
    "teamAbbr": "JPN",
    "appearances": 1,
    "goals": 0,
    "assists": 0,
    "shots": 0,
    "shotsOnTarget": 0,
    "saves": 0,
    "yellowCards": 0,
    "redCards": 0,
    "minutesPlayed": 0
  },
  "286347": {
    "name": "Daizen Maeda",
    "teamName": "Japan",
    "teamAbbr": "JPN",
    "appearances": 1,
    "goals": 0,
    "assists": 0,
    "shots": 0,
    "shotsOnTarget": 0,
    "saves": 0,
    "yellowCards": 0,
    "redCards": 0,
    "minutesPlayed": 0
  },
  "296982": {
    "name": "Mohamed Amine Ben Hamida",
    "teamName": "Tunisia",
    "teamAbbr": "TUN",
    "appearances": 1,
    "goals": 0,
    "assists": 0,
    "shots": 0,
    "shotsOnTarget": 0,
    "saves": 0,
    "yellowCards": 0,
    "redCards": 0,
    "minutesPlayed": 0
  },
  "299861": {
    "name": "Mohamed Hadj Mahmoud",
    "teamName": "Tunisia",
    "teamAbbr": "TUN",
    "appearances": 1,
    "goals": 0,
    "assists": 0,
    "shots": 0,
    "shotsOnTarget": 0,
    "saves": 0,
    "yellowCards": 0,
    "redCards": 0,
    "minutesPlayed": 0
  },
  "300007": {
    "name": "Hannibal Mejbri",
    "teamName": "Tunisia",
    "teamAbbr": "TUN",
    "appearances": 1,
    "goals": 0,
    "assists": 0,
    "shots": 1,
    "shotsOnTarget": 0,
    "saves": 0,
    "yellowCards": 0,
    "redCards": 0,
    "minutesPlayed": 0
  },
  "302944": {
    "name": "Anis Slimane",
    "teamName": "Tunisia",
    "teamAbbr": "TUN",
    "appearances": 1,
    "goals": 0,
    "assists": 0,
    "shots": 0,
    "shotsOnTarget": 0,
    "saves": 0,
    "yellowCards": 0,
    "redCards": 0,
    "minutesPlayed": 0
  },
  "303031": {
    "name": "Yuito Suzuki",
    "teamName": "Japan",
    "teamAbbr": "JPN",
    "appearances": 1,
    "goals": 0,
    "assists": 0,
    "shots": 0,
    "shotsOnTarget": 0,
    "saves": 0,
    "yellowCards": 0,
    "redCards": 0,
    "minutesPlayed": 0
  },
  "303702": {
    "name": "Sebastian Tounekti",
    "teamName": "Tunisia",
    "teamAbbr": "TUN",
    "appearances": 1,
    "goals": 0,
    "assists": 0,
    "shots": 0,
    "shotsOnTarget": 0,
    "saves": 0,
    "yellowCards": 0,
    "redCards": 0,
    "minutesPlayed": 0
  },
  "303848": {
    "name": "Omar Rekik",
    "teamName": "Tunisia",
    "teamAbbr": "TUN",
    "appearances": 1,
    "goals": 0,
    "assists": 0,
    "shots": 0,
    "shotsOnTarget": 0,
    "saves": 0,
    "yellowCards": 0,
    "redCards": 0,
    "minutesPlayed": 0,
    "headshot": "https://a.espncdn.com/i/headshots/soccer/players/full/303848.png"
  },
  "312924": {
    "name": "Tomoki Hayakawa",
    "teamName": "Japan",
    "teamAbbr": "JPN",
    "appearances": 1,
    "goals": 0,
    "assists": 0,
    "shots": 0,
    "shotsOnTarget": 0,
    "saves": 0,
    "yellowCards": 0,
    "redCards": 0,
    "minutesPlayed": 0
  },
  "317473": {
    "name": "Ismaël Gharbi",
    "teamName": "Tunisia",
    "teamAbbr": "TUN",
    "appearances": 1,
    "goals": 0,
    "assists": 0,
    "shots": 1,
    "shotsOnTarget": 0,
    "saves": 0,
    "yellowCards": 0,
    "redCards": 0,
    "minutesPlayed": 0
  },
  "323950": {
    "name": "Elias Saad",
    "teamName": "Tunisia",
    "teamAbbr": "TUN",
    "appearances": 1,
    "goals": 0,
    "assists": 0,
    "shots": 0,
    "shotsOnTarget": 0,
    "saves": 0,
    "yellowCards": 0,
    "redCards": 0,
    "minutesPlayed": 0
  },
  "324510": {
    "name": "Elias Achouri",
    "teamName": "Tunisia",
    "teamAbbr": "TUN",
    "appearances": 1,
    "goals": 0,
    "assists": 0,
    "shots": 0,
    "shotsOnTarget": 0,
    "saves": 0,
    "yellowCards": 0,
    "redCards": 0,
    "minutesPlayed": 0
  },
  "333663": {
    "name": "Junnosuke Suzuki",
    "teamName": "Japan",
    "teamAbbr": "JPN",
    "appearances": 1,
    "goals": 0,
    "assists": 0,
    "shots": 0,
    "shotsOnTarget": 0,
    "saves": 0,
    "yellowCards": 0,
    "redCards": 0,
    "minutesPlayed": 0
  },
  "345975": {
    "name": "Moutaz Neffati",
    "teamName": "Tunisia",
    "teamAbbr": "TUN",
    "appearances": 1,
    "goals": 0,
    "assists": 0,
    "shots": 0,
    "shotsOnTarget": 0,
    "saves": 0,
    "yellowCards": 0,
    "redCards": 0,
    "minutesPlayed": 0
  },
  "346208": {
    "name": "Keisuke Goto",
    "teamName": "Japan",
    "teamAbbr": "JPN",
    "appearances": 1,
    "goals": 0,
    "assists": 0,
    "shots": 0,
    "shotsOnTarget": 0,
    "saves": 0,
    "yellowCards": 0,
    "redCards": 0,
    "minutesPlayed": 0
  },
  "357030": {
    "name": "Kaishu Sano",
    "teamName": "Japan",
    "teamAbbr": "JPN",
    "appearances": 1,
    "goals": 0,
    "assists": 1,
    "shots": 0,
    "shotsOnTarget": 0,
    "saves": 0,
    "yellowCards": 0,
    "redCards": 0,
    "minutesPlayed": 0
  },
  "362959": {
    "name": "Kento Shiogai",
    "teamName": "Japan",
    "teamAbbr": "JPN",
    "appearances": 1,
    "goals": 0,
    "assists": 0,
    "shots": 0,
    "shotsOnTarget": 0,
    "saves": 0,
    "yellowCards": 0,
    "redCards": 0,
    "minutesPlayed": 0
  },
  "396085": {
    "name": "Hazem Mastouri",
    "teamName": "Tunisia",
    "teamAbbr": "TUN",
    "appearances": 1,
    "goals": 0,
    "assists": 0,
    "shots": 0,
    "shotsOnTarget": 0,
    "saves": 0,
    "yellowCards": 0,
    "redCards": 0,
    "minutesPlayed": 0
  },
  "404769": {
    "name": "Khalil Ayari",
    "teamName": "Tunisia",
    "teamAbbr": "TUN",
    "appearances": 1,
    "goals": 0,
    "assists": 0,
    "shots": 0,
    "shotsOnTarget": 0,
    "saves": 0,
    "yellowCards": 0,
    "redCards": 0,
    "minutesPlayed": 0
  },
  "405591": {
    "name": "Rayan Elloumi",
    "teamName": "Tunisia",
    "teamAbbr": "TUN",
    "appearances": 1,
    "goals": 0,
    "assists": 0,
    "shots": 0,
    "shotsOnTarget": 0,
    "saves": 0,
    "yellowCards": 0,
    "redCards": 0,
    "minutesPlayed": 0
  },
  "410358": {
    "name": "Adem Arous",
    "teamName": "Tunisia",
    "teamAbbr": "TUN",
    "appearances": 1,
    "goals": 0,
    "assists": 0,
    "shots": 0,
    "shotsOnTarget": 0,
    "saves": 0,
    "yellowCards": 0,
    "redCards": 0,
    "minutesPlayed": 0
  },
  "420888": {
    "name": "Mouhib Chamakh",
    "teamName": "Tunisia",
    "teamAbbr": "TUN",
    "appearances": 1,
    "goals": 0,
    "assists": 0,
    "shots": 0,
    "shotsOnTarget": 0,
    "saves": 0,
    "yellowCards": 0,
    "redCards": 0,
    "minutesPlayed": 0
  },
  "420890": {
    "name": "Raed Chikhaoui",
    "teamName": "Tunisia",
    "teamAbbr": "TUN",
    "appearances": 1,
    "goals": 0,
    "assists": 0,
    "shots": 0,
    "shotsOnTarget": 0,
    "saves": 0,
    "yellowCards": 0,
    "redCards": 0,
    "minutesPlayed": 0
  }
}